AUTHORS
ChangeLog
LICENSE
MANIFEST.in
NOTICE
README.md
requirements.txt
setup.cfg
setup.py
bin/run-examples
bin/run-isolated-tests
bin/verify-license-headers
spotify_tensorflow/__init__.py
spotify_tensorflow/dataset.py
spotify_tensorflow/example_decoders.py
spotify_tensorflow/featran.py
spotify_tensorflow/tf_schema_utils.py
spotify_tensorflow.egg-info/PKG-INFO
spotify_tensorflow.egg-info/SOURCES.txt
spotify_tensorflow.egg-info/dependency_links.txt
spotify_tensorflow.egg-info/entry_points.txt
spotify_tensorflow.egg-info/not-zip-safe
spotify_tensorflow.egg-info/pbr.json
spotify_tensorflow.egg-info/requires.txt
spotify_tensorflow.egg-info/top_level.txt
spotify_tensorflow/luigi/__init__.py
spotify_tensorflow/luigi/python_dataflow_task.py
spotify_tensorflow/luigi/tensorflow_task.py
spotify_tensorflow/luigi/tfx_task.py
spotify_tensorflow/luigi/utils.py
spotify_tensorflow/scripts/__init__.py
spotify_tensorflow/scripts/tfr_read.py
spotify_tensorflow/tfx/__init__.py
spotify_tensorflow/tfx/tfdv.py
spotify_tensorflow/tfx/tft.py
spotify_tensorflow/tfx/utils.py
tests/README.md
tests/__init__.py
tests/dataset_test.py
tests/example_decoders_test.py
tests/featran_test.py
tests/luigi_utils_test.py
tests/python_dataflow_task_test.py
tests/scripts_tfr_read.py
tests/tensorflow_task_test.py
tests/test_utils.py
tests/tf_schema_utils_test.py
tests/tfdv_test.py
tests/tft_test.py
tests/tfx_task_test.py
tests/tfx_utils_test.py
tests/resources/tf-test-resource/.gitignore
tests/resources/tf-test-resource/README.md
tests/resources/tf-test-resource/build.sbt
tests/resources/tf-test-resource/scalastyle-config.xml
tests/resources/tf-test-resource/project/build.properties
tests/resources/tf-test-resource/project/plugins.sbt
tests/resources/tf-test-resource/src/main/resources/iris.data
tests/resources/tf-test-resource/src/main/resources/log4j.properties
tests/resources/tf-test-resource/src/main/scala/com/spotify/GenerateIrisTFRecords.scala
tests/resources/tf-test-resource/src/main/scala/com/spotify/GenerateTFRecords.scala
tests/resources/tf-test-resource/tf-records-iris/eval/_inferred_schema.pb
tests/resources/tf-test-resource/tf-records-iris/eval/_stats.pb
tests/resources/tf-test-resource/tf-records-iris/eval/part-00000-of-00003.tfrecords
tests/resources/tf-test-resource/tf-records-iris/eval/part-00001-of-00003.tfrecords
