Metadata-Version: 2.1
Name: spotify-tensorflow
Version: 0.7.6
Summary: Spotify-specific helpers for TensorFlow
Home-page: https://github.com/spotify/spotify-tensorflow
License: Apache-2
Keywords: tensorflow,utils
Platform: UNKNOWN
Classifier: Development Status :: 3 - Alpha
Classifier: Intended Audience :: Developers
Classifier: Intended Audience :: Information Technology
Classifier: License :: OSI Approved :: Apache Software License
Classifier: Operating System :: OS Independent
Classifier: Programming Language :: Python
Classifier: Programming Language :: Python :: 2.7
Provides-Extra: luigi
Provides-Extra: examples
Provides-Extra: testing
Provides-Extra: lint
